eyekit/__init__.py
eyekit/_bidi.py
eyekit/_color.py
eyekit/_font.py
eyekit/_snap.py
eyekit/_version.py
eyekit/fixation.py
eyekit/io.py
eyekit/measure.py
eyekit/text.py
eyekit/tools.py
eyekit/vis.py
eyekit-0.7.0.dist-info/LICENSE
eyekit-0.7.0.dist-info/METADATA
eyekit-0.7.0.dist-info/WHEEL
eyekit-0.7.0.dist-info/top_level.txt
eyekit-0.7.0.dist-info/RECORD
