Metadata-Version: 2.2
Name: eyekit
Version: 0.7.0
Summary: A Python package for analyzing reading behavior using eyetracking data
Author-email: Jon Carr <jon.carr@rhul.ac.uk>
License: GPLv3
Project-URL: Homepage, https://github.com/jwcarr/eyekit
Project-URL: Documentation, https://jwcarr.github.io/eyekit/
Classifier: Programming Language :: Python :: 3
Classifier: License :: OSI Approved :: GNU General Public License v3 (GPLv3)
Classifier: Operating System :: OS Independent
Classifier: Development Status :: 4 - Beta
Classifier: Intended Audience :: Science/Research
Classifier: Topic :: Scientific/Engineering :: Human Machine Interfaces
Classifier: Topic :: Scientific/Engineering :: Visualization
Classifier: Topic :: Text Processing :: Fonts
Classifier: Topic :: Text Processing :: Linguistic
Requires-Python: >=3.8
License-File: LICENSE
Requires-Dist: cairocffi>=1.1
